djkr8/AGENTS.md
djkr8/__init__.py
djkr8/bpm.py
djkr8/camelot.py
djkr8/cli.py
djkr8/models.py
djkr8/optimizer.py
djkr8/py.typed
djkr8/rekordbox.py
djkr8-1.5.0.dist-info/WHEEL
djkr8-1.5.0.dist-info/entry_points.txt
djkr8-1.5.0.dist-info/METADATA
djkr8-1.5.0.dist-info/RECORD
