Metadata-Version: 2.3
Name: djkr8
Version: 1.5.0
Summary: DJ playlist optimizer using Google OR-Tools for harmonic mixing and BPM matching
Author: Sage Choi
Author-email: Sage Choi <sage.choi@gmail.com>
License: MIT License
Requires-Dist: ortools>=9.8.3296
Requires-Dist: pyrekordbox>=0.1.0
Requires-Dist: pytest>=7.4.0 ; extra == 'dev'
Requires-Dist: pytest-cov>=4.1.0 ; extra == 'dev'
Requires-Python: >=3.10
Project-URL: Homepage, https://github.com/schoi80/djkr8
Project-URL: Repository, https://github.com/schoi80/djkr8
Provides-Extra: dev
